belief_propagation/__init__.py
belief_propagation/algorithm.py
belief_propagation/channel_models.py
belief_propagation/graph.py
belief_propagation/node.py
belief_propagation_ldpc-1.0.1.dist-info/LICENSE
belief_propagation_ldpc-1.0.1.dist-info/METADATA
belief_propagation_ldpc-1.0.1.dist-info/WHEEL
belief_propagation_ldpc-1.0.1.dist-info/top_level.txt
belief_propagation_ldpc-1.0.1.dist-info/RECORD
