Metadata-Version: 2.1
Name: belief-propagation-ldpc
Version: 1.0.1
Summary: Belief propagation on Tanner graphs. Implements an LLR based LDPC decoder.
Home-page: https://github.com/YairMZ/belief_propagation
Author: Yair Mazal
Author-email: yairmazal@gmail.com
License: MIT
Keywords: LDPC,Belief Propagation,SPA,Tanner Graph
Platform: UNKNOWN
Classifier: License :: OSI Approved :: MIT License
Classifier: Programming Language :: Python :: 3
Classifier: Intended Audience :: Science/Research
Classifier: Topic :: Scientific/Engineering
License-File: LICENSE
Requires-Dist: numpy
Requires-Dist: networkx
